chogame/__init__.py
chogame/techdemo.py
chogame/techdemo2.py
chogame-0.0.1.dist-info/LICENSE.md
chogame-0.0.1.dist-info/METADATA
chogame-0.0.1.dist-info/WHEEL
chogame-0.0.1.dist-info/top_level.txt
chogame-0.0.1.dist-info/RECORD
