Metadata-Version: 2.1
Name: chogame
Version: 0.0.1
Summary: A module for creating choice based games.
Home-page: https://github.com/justamirror/CHOgame/
Author: JAM47
Author-email: Eren0078@outlook.com
License: UNKNOWN
Project-URL: Bug Tracker, https://github.com/justamirror/CHOgame/issues
Platform: UNKNOWN
Classifier: Programming Language :: Python :: 3
Classifier: License :: OSI Approved :: MIT License
Classifier: Operating System :: OS Independent
Requires-Python: >=3.6
